leap_net/__init__.py
leap_net/agents/__init__.py
leap_net/agents/randomAct1.py
leap_net/agents/randomAct2.py
leap_net/agents/randomN1.py
leap_net/agents/randomN2.py
leap_net/agents/randomNN1.py
leap_net/agents/randomRefAct1.py
leap_net/agents/randomRefSub1.py
leap_net/agents/randomSub1.py
leap_net/agents/randomSub2.py
leap_net/generate_data/__init__.py
leap_net/generate_data/generate_dataset.py
leap_net/keras/__init__.py
leap_net/keras/ltau.py
leap_net/keras/ltauNoAdd.py
leap_net/keras/resNetLayer.py
leap_net/metrics/__init__.py
leap_net/metrics/mape.py
leap_net/metrics/mape_quantile.py
leap_net/metrics/nrmse.py
leap_net/metrics/pearsonr.py
leap_net/proxy/__init__.py
leap_net/proxy/agentWithProxy.py
leap_net/proxy/baseNNProxy.py
leap_net/proxy/baseProxy.py
leap_net/proxy/evaluate_proxy_case_118.py
leap_net/proxy/evaluate_proxy_case_14.py
leap_net/proxy/proxyBackend.py
leap_net/proxy/proxyLeapNet.py
leap_net/proxy/train_proxy_case_118.py
leap_net/proxy/train_proxy_case_14.py
leap_net/proxy/utils.py
leap_net/test/__init__.py
leap_net/test/test_Agent.py
leap_net/test/test_LeapNetProxy.py
leap_net/test/test_LeapNet_keras.py
leap_net/test/test_LeapNet_tf_keras.py
leap_net/test/test_RandomAct1.py
leap_net/test/test_RandomAct2.py
leap_net/tf_keras/__init__.py
leap_net/tf_keras/ltau.py
leap_net/tf_keras/ltauNoAdd.py
leap_net/tf_keras/resNetLayer.py
leap_net/tf_keras/kerasutils/__init__.py
leap_net/tf_keras/kerasutils/multipleDasetCallBacks.py
leap_net-0.1.1.dist-info/AUTHORS.txt
leap_net-0.1.1.dist-info/LICENSE
leap_net-0.1.1.dist-info/METADATA
leap_net-0.1.1.dist-info/WHEEL
leap_net-0.1.1.dist-info/top_level.txt
leap_net-0.1.1.dist-info/RECORD
