Metadata-Version: 2.1
Name: leap_net
Version: 0.1.1
Summary: An implementation in keras 3.0 (and tensorflow keras) of the LeapNet model
Home-page: https://github.com/bdonnot/leap_net
Author: Benjamin DONNOT
Author-email: benjamin.donnot@rte-france.com
License: Mozilla Public License 2.0 (MPL 2.0)
Keywords: LEAP-Net guided-dropout dropout resnet
Classifier: Development Status :: 4 - Beta
Classifier: Programming Language :: Python :: 3.8
Classifier: Programming Language :: Python :: 3.9
Classifier: Programming Language :: Python :: 3.10
Classifier: Programming Language :: Python :: 3.11
Classifier: Programming Language :: Python :: 3.12
Classifier: License :: OSI Approved :: Mozilla Public License 2.0 (MPL 2.0)
Classifier: Intended Audience :: Developers
Classifier: Intended Audience :: Education
Classifier: Intended Audience :: Science/Research
Classifier: Natural Language :: English
Requires-Python: >=3.8
License-File: LICENSE
License-File: AUTHORS.txt
Requires-Dist: keras >=3
Requires-Dist: numpy
Requires-Dist: scipy
Requires-Dist: packaging
Provides-Extra: recommended
Requires-Dist: grid2op ; extra == 'recommended'
Requires-Dist: pandas ; extra == 'recommended'
Requires-Dist: tqdm ; extra == 'recommended'
Requires-Dist: scikit-learn ; extra == 'recommended'
Requires-Dist: tensorflow ; extra == 'recommended'
Provides-Extra: test
Requires-Dist: grid2op ; extra == 'test'
Requires-Dist: pandas ; extra == 'test'
Requires-Dist: tqdm ; extra == 'test'
Requires-Dist: scikit-learn ; extra == 'test'
